{
  "name" : "flydubai",
  "code" : "FZ",
  "web" : "https://www.flydubai.com/en/",
  "lounge" : "N/A",
  "reservationsPhone" : "+7 8 800 555 2833",
  "frequentFlyerProgram" : "OPEN",
  "alliance" : "N/A",
  "magazine" : null,
  "aircrafts" : [ {
    "type" : "NARROW_BODY_JETS",
    "name" : "Boeing 737-800 (738) Layout 1",
    "amenities" : [ "FOOD", "INTERNET", "VIDEO", "AUDIO" ],
    "seats" : [ {
      "seatClass" : "Economy",
      "numSeats" : 189
    } ]
  }, {
    "type" : "NARROW_BODY_JETS",
    "name" : "Boeing 737-800 (738) Layout 2",
    "amenities" : [ "FOOD", "INTERNET", "AC_POWER", "VIDEO", "AUDIO" ],
    "seats" : [ {
      "seatClass" : "Business",
      "numSeats" : 12
    }, {
      "seatClass" : "Economy",
      "numSeats" : 162
    } ]
  } ],
  "popularDestinations" : [ "Washington DC", "Orlando", "Chicago", "Las Vegas", "San Francisco", "Honolulu", "Mexico", "Toronto", "London", "New York City" ]
}