{
  "name" : "Jet2",
  "code" : "LS",
  "web" : "https://www.jet2.com/",
  "lounge" : "Lounge Pass",
  "reservationsPhone" : "+43 800 9097 20",
  "frequentFlyerProgram" : "MyJet2 Travel Club",
  "alliance" : "N/A",
  "magazine" : null,
  "aircrafts" : [ {
    "type" : "WIDE_BODY_JETS",
    "name" : "Airbus A330-200",
    "amenities" : [ "FOOD" ],
    "seats" : [ {
      "seatClass" : "Economy",
      "numSeats" : 327
    } ]
  }, {
    "type" : "NARROW_BODY_JETS",
    "name" : "Airbus A321 (321) Layout 1",
    "amenities" : [ "FOOD", "VIDEO" ],
    "seats" : [ {
      "seatClass" : "Economy",
      "numSeats" : 218
    } ]
  }, {
    "type" : "NARROW_BODY_JETS",
    "name" : "Airbus A321 (321) Layout 2",
    "amenities" : [ "FOOD", "VIDEO" ],
    "seats" : [ {
      "seatClass" : "Economy",
      "numSeats" : 220
    } ]
  }, {
    "type" : "NARROW_BODY_JETS",
    "name" : "Boeing 737-300 (733)",
    "amenities" : [ "FOOD" ],
    "seats" : [ {
      "seatClass" : "Economy",
      "numSeats" : 148
    } ]
  }, {
    "type" : "NARROW_BODY_JETS",
    "name" : "Boeing 737-800 (738)",
    "amenities" : [ "FOOD" ],
    "seats" : [ {
      "seatClass" : "Economy",
      "numSeats" : 189
    } ]
  }, {
    "type" : "NARROW_BODY_JETS",
    "name" : "Boeing 757-200 (752)",
    "amenities" : [ "FOOD" ],
    "seats" : [ {
      "seatClass" : "Economy",
      "numSeats" : 235
    } ]
  } ],
  "popularDestinations" : [ "Washington DC", "Orlando", "Chicago", "Las Vegas", "San Francisco", "Honolulu", "Mexico", "Toronto", "London", "New York City" ]
}