{
  "name" : "Luxair",
  "code" : "LG",
  "web" : "https://www.luxair.lu/homepage",
  "lounge" : "The Lounge",
  "reservationsPhone" : "00800 2456 4242",
  "frequentFlyerProgram" : "Miles & More",
  "alliance" : "N/A",
  "magazine" : "Flydoscope",
  "aircrafts" : [ {
    "type" : "NARROW_BODY_JETS",
    "name" : "Boeing 737-700 (73G)",
    "amenities" : [ "FOOD" ],
    "seats" : [ {
      "seatClass" : "Economy",
      "numSeats" : 141
    } ]
  }, {
    "type" : "NARROW_BODY_JETS",
    "name" : "Boeing 737-800 (738)",
    "amenities" : [ "FOOD" ],
    "seats" : [ {
      "seatClass" : "Economy",
      "numSeats" : 186
    } ]
  }, {
    "type" : "TURBOPROPS",
    "name" : "Bombardier Q400 (DH4)",
    "amenities" : [ "FOOD" ],
    "seats" : [ {
      "seatClass" : "Economy",
      "numSeats" : 76
    } ]
  } ],
  "popularDestinations" : [ "Washington DC", "Orlando", "Chicago", "Las Vegas", "San Francisco", "Honolulu", "Mexico", "Toronto", "London", "New York City" ]
}